{
    "deckId": "090a0deebc",
    "deckContributor": "1030015",
    "deckName": "红莲魔龙",
    "deckType": "",
    "deckRank": 0,
    "deckLike": 1,
    "deckUploadDate": 1738838315000,
    "deckUpdateDate": 1752727416000,
    "deckCoverCard1": -1,
    "deckCoverCard2": 0,
    "deckCoverCard3": 0,
    "deckCase": 0,
    "deckProtector": 0,
    "deckMainSerial": "",
    "deckYdk": "###1030015\n\n###090a0deebc",
    "userId": 1030015,
    "isPublic": true,
    "description": "NULL",
    "isDelete": false
}