{
    "deckId": "3d2b93b4ec",
    "deckContributor": "1040668",
    "deckName": "闪刀姬之居合斩",
    "deckType": "",
    "deckRank": 0,
    "deckLike": 0,
    "deckUploadDate": 1740831172000,
    "deckUpdateDate": 1753194197000,
    "deckCoverCard1": -1,
    "deckCoverCard2": 0,
    "deckCoverCard3": 0,
    "deckCase": 0,
    "deckProtector": 0,
    "deckMainSerial": "",
    "deckYdk": "###1040668\n\n###3d2b93b4ec",
    "userId": 1040668,
    "isPublic": true,
    "description": "NULL",
    "isDelete": false
}