{
    "deckId": "b052b0784b",
    "deckContributor": "788702",
    "deckName": "炎",
    "deckType": "",
    "deckRank": 0,
    "deckLike": 0,
    "deckUploadDate": 1742830406000,
    "deckUpdateDate": 1753620897000,
    "deckCoverCard1": -1,
    "deckCoverCard2": 0,
    "deckCoverCard3": 0,
    "deckCase": 0,
    "deckProtector": 0,
    "deckMainSerial": "",
    "deckYdk": "###788702\n\n###b052b0784b",
    "userId": 788702,
    "isPublic": true,
    "description": "NULL",
    "isDelete": false
}