{
    "deckId": "b67b643417",
    "deckContributor": "743253",
    "deckName": "雷火",
    "deckType": "",
    "deckRank": 0,
    "deckLike": 0,
    "deckUploadDate": 1729007883000,
    "deckUpdateDate": 1753019000000,
    "deckCoverCard1": -1,
    "deckCoverCard2": 0,
    "deckCoverCard3": 0,
    "deckCase": 0,
    "deckProtector": 0,
    "deckMainSerial": "",
    "deckYdk": "###743253\n\n###b67b643417",
    "userId": 743253,
    "isPublic": true,
    "description": "NULL",
    "isDelete": false
}