{
    "deckId": "c8a7f0e214",
    "deckContributor": "xLingHolic",
    "deckName": "泛用·超量4",
    "deckType": "",
    "deckRank": 0,
    "deckLike": 0,
    "deckUploadDate": 1740291634000,
    "deckUpdateDate": 1740927960000,
    "deckCoverCard1": 0,
    "deckCoverCard2": 0,
    "deckCoverCard3": 0,
    "deckCase": 1082001,
    "deckProtector": 1070001,
    "deckMainSerial": "",
    "deckYdk": "#created by MDPro3\n#main\n#extra\n74294676\n55285840\n82697249\n42752141\n90590303\n90590304\n6983839\n72167543\n31437713\n86331741\n67557908\n46772449\n37926346\n21044178\n63504681\n!side\n66011101\n62517849\n93568288\n74393852\n41375811\n#case\n#1082001\n#protector\n#1070001\n#field\n#1090001\n#grave\n#1100001\n#stand\n#1110001\n#mate\n#1000001\n##c8a7f0e214\n###1006148",
    "userId": 1006148,
    "isPublic": true,
    "description": "NULL",
    "isDelete": false
}