{
    "deckId": "cc0c9d6056",
    "deckContributor": "没有手坑",
    "deckName": "神",
    "deckType": "",
    "deckRank": 0,
    "deckLike": 0,
    "deckUploadDate": 1738303288000,
    "deckUpdateDate": 1738303288000,
    "deckCoverCard1": 0,
    "deckCoverCard2": 0,
    "deckCoverCard3": 0,
    "deckCase": 1080001,
    "deckProtector": 1070001,
    "deckMainSerial": "",
    "deckYdk": "#created by mdpro3\n#main\n#extra\n!side\n#pickup\n#case\n1080001#\n#protector\n1070001#\n#field\n1090001#\n#grave\n1100001#\n#stand\n1110001#\n#mate\n1000001#\n##cc0c9d6056\n###1033889",
    "userId": 1033889,
    "isPublic": true,
    "description": "NULL",
    "isDelete": false
}