{
    "deckId": "fd6a25cf92",
    "deckContributor": "1001280",
    "deckName": "堕天使 ",
    "deckType": "",
    "deckRank": 0,
    "deckLike": 1,
    "deckUploadDate": 1728108123000,
    "deckUpdateDate": 1753781284000,
    "deckCoverCard1": -1,
    "deckCoverCard2": 0,
    "deckCoverCard3": 0,
    "deckCase": 0,
    "deckProtector": 0,
    "deckMainSerial": "",
    "deckYdk": "###1001280\n\n###fd6a25cf92",
    "userId": 1001280,
    "isPublic": true,
    "description": "NULL",
    "isDelete": false
}